sage_func/__init__.py
sage_func/config.py
sage_func/sageai.py
sage_func/services/base_url.py
sage_func/services/defaultvectordb_service.py
sage_func/services/openai_service.py
sage_func/tests/integration.py
sage_func/tests/main.py
sage_func/tests/unit.py
sage_func/tests/utils.py
sage_func/types/abstract_vectordb.py
sage_func/types/function.py
sage_func/types/log_level.py
sage_func/utils/file_utilities.py
sage_func/utils/format_config_args.py
sage_func/utils/inspection_utilities.py
sage_func/utils/logger.py
sage_func/utils/model_utilities.py
sage_func/utils/openai_utilities.py
sage_func-0.1.5.dist-info/LICENSE
sage_func-0.1.5.dist-info/METADATA
sage_func-0.1.5.dist-info/WHEEL
sage_func-0.1.5.dist-info/entry_points.txt
sage_func-0.1.5.dist-info/RECORD
