Metadata-Version: 2.1
Name: sage-func
Version: 0.1.5
Summary: Folder-based functions for GPT 3.5/4 function calling with Pydantic support
License: MIT
Keywords: python,openai,functions,chatgpt,gpt4,genai,function-calling
Author: JUNIORCO
Author-email: sami@lasso.gg
Requires-Python: >=3.9,<3.12
Classifier: License :: OSI Approved :: MIT License
Classifier: Programming Language :: Python :: 3
Classifier: Programming Language :: Python :: 3.9
Classifier: Programming Language :: Python :: 3.10
Classifier: Programming Language :: Python :: 3.11
Requires-Dist: openai (>=0.27.0)
Requires-Dist: pydantic (>=1.6,<=1.10.12)
Requires-Dist: qdrant-client (>=1.4.0)
